quantum_pipeline-1.2.5.dist-info/METADATA
quantum_pipeline-1.2.5.dist-info/WHEEL
quantum_pipeline-1.2.5.dist-info/entry_points.txt
quantum_pipeline-1.2.5.dist-info/licenses/LICENSE
quantum_pipeline/__init__.py
quantum_pipeline/configs/defaults.py
quantum_pipeline/configs/module/backend.py
quantum_pipeline/configs/module/producer.py
quantum_pipeline/configs/module/security.py
quantum_pipeline/configs/parsing/argparser.py
quantum_pipeline/configs/parsing/configuration_manager.py
quantum_pipeline/configs/settings.py
quantum_pipeline/drivers/__init__.py
quantum_pipeline/drivers/basis_sets.py
quantum_pipeline/drivers/molecule_loader.py
quantum_pipeline/features/circuit.py
quantum_pipeline/mappers/__init__.py
quantum_pipeline/mappers/jordan_winger_mapper.py
quantum_pipeline/mappers/mapper.py
quantum_pipeline/report/configuration.py
quantum_pipeline/report/content_builder.py
quantum_pipeline/report/renderer.py
quantum_pipeline/report/report_generator.py
quantum_pipeline/runners/runner.py
quantum_pipeline/runners/vqe_runner.py
quantum_pipeline/solvers/__init__.py
quantum_pipeline/solvers/solver.py
quantum_pipeline/solvers/vqe_solver.py
quantum_pipeline/stream/kafka_interface.py
quantum_pipeline/stream/kafka_security.py
quantum_pipeline/stream/serialization/interfaces/vqe.py
quantum_pipeline/stream/serialization/schemas/vqe_decorated_result.avsc
quantum_pipeline/stream/serialization/schemas/vqe_initial.avsc
quantum_pipeline/stream/serialization/schemas/vqe_molecule.avsc
quantum_pipeline/stream/serialization/schemas/vqe_process.avsc
quantum_pipeline/stream/serialization/schemas/vqe_result.avsc
quantum_pipeline/structures/vqe_observation.py
quantum_pipeline/utils/__init__.py
quantum_pipeline/utils/dir.py
quantum_pipeline/utils/logger.py
quantum_pipeline/utils/schema_registry.py
quantum_pipeline/utils/timer.py
quantum_pipeline/visual/__init__.py
quantum_pipeline/visual/ansatz.py
quantum_pipeline/visual/energy.py
quantum_pipeline/visual/molecule.py
quantum_pipeline/visual/operator.py
quantum_pipeline-1.2.5.dist-info/RECORD
