Metadata-Version: 2.1
Name: quantum-pipeline
Version: 1.2.5
Summary: Framework for running, monitoring and analysing quantum algorithms.
Author-Email: Piotr Krzysztof <piotrlis555@gmail.com>
Maintainer-Email: Piotr Krzysztof <piotrlis555@gmail.com>
License: MIT
Classifier: Development Status :: 4 - Beta
Classifier: Intended Audience :: Science/Research
Classifier: Topic :: Scientific/Engineering :: Physics
Classifier: Topic :: Scientific/Engineering :: Chemistry
Classifier: Topic :: Scientific/Engineering :: Visualization
Classifier: License :: OSI Approved :: MIT License
Classifier: Programming Language :: Python :: 3.10
Classifier: Programming Language :: Python :: 3.11
Classifier: Programming Language :: Python :: 3.12
Classifier: Operating System :: POSIX :: Linux
Project-URL: Homepage, https://github.com/straightchlorine/quantum-pipeline
Requires-Python: <3.13,>=3.10
Requires-Dist: qiskit>=1.4.2
Requires-Dist: qiskit-ibm-runtime>=0.37.0
Requires-Dist: qiskit-aer>=0.15.1
Requires-Dist: qiskit-nature>=0.7.2
Requires-Dist: pyscf>=2.8.0
Requires-Dist: reportlab>=4.3.1
Requires-Dist: matplotlib>=3.10.0
Requires-Dist: scipy>=1.15.2
Requires-Dist: numpy>=2.2.3
Requires-Dist: pyscf>=2.8.0
Requires-Dist: avro>=1.12.0
Requires-Dist: kafka-python-ng>=2.2.3
Requires-Dist: Requests>=2.32.3
Requires-Dist: pyspark>=3.5.5
Requires-Dist: cryptography>=44.0.1
Requires-Dist: Jinja2>=3.1.6
Provides-Extra: dev
Requires-Dist: debugpy>=1.8.12; extra == "dev"
Requires-Dist: pytest>=8.3.4; extra == "dev"
